image_processing_dev/__init__.py
image_processing_dev/image_processor.py
image_processing_dev-0.1.0.dist-info/METADATA
image_processing_dev-0.1.0.dist-info/WHEEL
image_processing_dev-0.1.0.dist-info/top_level.txt
image_processing_dev-0.1.0.dist-info/RECORD
